Workbook

Sheet Parámetros
A1: Parámetro | B1: Valor | C1: Nota
A2: Plan de n8n | B2: Pro | C2: Nube gestionada
A3: Precio del plan (EUR por mes) | B3: 50 | C3: Facturación anual, página oficial de precios (octubre de 2026)
A4: Cupo de ejecuciones por mes | B4: 10000 | C4: Al superarlo, las ejecuciones nuevas fallan
A5: Tipo de cambio EUR a USD | B5: 1.15 | C5: Valor de ejemplo: reemplazar por la cotización del día
A6: Modelo A: USD por millón de tokens de entrada | B6: 3 | C6: Precio hipotético de un modelo de gama alta
A7: Modelo A: USD por millón de tokens de salida | B7: 15 | C7: Precio hipotético
A8: Modelo B: USD por millón de tokens de entrada | B8: 0.25 | C8: Precio hipotético de un modelo económico
A9: Modelo B: USD por millón de tokens de salida | B9: 1.25 | C9: Precio hipotético
A10: API de vuelos: USD por consulta | B10: 0.002 | C10: Precio hipotético del proveedor externo

Sheet Flujos
A1: Flujo | B1: Trigger | C1: Ejecuciones por mes | D1: Modelo de IA | E1: Tokens de entrada por ejecución | F1: Tokens de salida por ejecución | G1: Consultas a API paga por ejecución | H1: Crece con las reservas
A2: F1 Confirmación de reservas | B2: Webhook de la plataforma de reservas | C2: 1800 | D2: Ninguno | E2: 0 | F2: 0 | G2: 0 | H2: Sí
A3: F2 Clasificación de consultas | B3: Email entrante | C3: 3000 | D3: Modelo A | E3: 1200 | F3: 200 | G3: 0 | H3: Sí
A4: F3 Recordatorios de pago | B4: Programado cada hora | C4: 720 | D4: Ninguno | E4: 0 | F4: 0 | G4: 0 | H4: Sí
A5: F4 Monitor de precios de vuelos | B5: Programado cada 15 minutos | C5: 2880 | D5: Ninguno | E5: 0 | F5: 0 | G5: 1 | H5: No

Sheet Costo mensual
A1: Flujo | B1: Ejecuciones | C1: Parte del cupo usado | D1: Plataforma prorrateada (USD) | E1: IA (USD) | F1: API externa (USD) | G1: Total del flujo (USD) | H1: Costo por ejecución (USD) | I1: Parte del gasto total
A2: =Flujos!A2 -> F1 Confirmación de reservas | B2: =Flujos!C2 -> 1800 | C2: =B2/SUM($B$2:$B$5) -> 0.21428571 | D2: =C2*Parámetros!$B$3*Parámetros!$B$5 -> 12.321429 | E2: =IF(Flujos!D2="Modelo A",B2*(Flujos!E2*Parámetros!$B$6+Flujos!F2*Parámetros!$B$7)/1000000,IF(Flujos!D2="Modelo B",B2*(Flujos!E2*Parámetros!$B$8+Flujos!F2*Parámetros!$B$9)/1000000,0)) -> 0 | F2: =B2*Flujos!G2*Parámetros!$B$10 -> 0 | G2: =D2+E2+F2 -> 12.321429 | H2: =G2/B2 -> 0.0068452381 | I2: =G2/$G$6 -> 0.14834371
A3: =Flujos!A3 -> F2 Clasificación de consultas | B3: =Flujos!C3 -> 3000 | C3: =B3/SUM($B$2:$B$5) -> 0.35714286 | D3: =C3*Parámetros!$B$3*Parámetros!$B$5 -> 20.535714 | E3: =IF(Flujos!D3="Modelo A",B3*(Flujos!E3*Parámetros!$B$6+Flujos!F3*Parámetros!$B$7)/1000000,IF(Flujos!D3="Modelo B",B3*(Flujos!E3*Parámetros!$B$8+Flujos!F3*Parámetros!$B$9)/1000000,0)) -> 19.8 | F3: =B3*Flujos!G3*Parámetros!$B$10 -> 0 | G3: =D3+E3+F3 -> 40.335714 | H3: =G3/B3 -> 0.013445238 | I3: =G3/$G$6 -> 0.48562141
A4: =Flujos!A4 -> F3 Recordatorios de pago | B4: =Flujos!C4 -> 720 | C4: =B4/SUM($B$2:$B$5) -> 0.085714286 | D4: =C4*Parámetros!$B$3*Parámetros!$B$5 -> 4.9285714 | E4: =IF(Flujos!D4="Modelo A",B4*(Flujos!E4*Parámetros!$B$6+Flujos!F4*Parámetros!$B$7)/1000000,IF(Flujos!D4="Modelo B",B4*(Flujos!E4*Parámetros!$B$8+Flujos!F4*Parámetros!$B$9)/1000000,0)) -> 0 | F4: =B4*Flujos!G4*Parámetros!$B$10 -> 0 | G4: =D4+E4+F4 -> 4.9285714 | H4: =G4/B4 -> 0.0068452381 | I4: =G4/$G$6 -> 0.059337484
A5: =Flujos!A5 -> F4 Monitor de precios de vuelos | B5: =Flujos!C5 -> 2880 | C5: =B5/SUM($B$2:$B$5) -> 0.34285714 | D5: =C5*Parámetros!$B$3*Parámetros!$B$5 -> 19.714286 | E5: =IF(Flujos!D5="Modelo A",B5*(Flujos!E5*Parámetros!$B$6+Flujos!F5*Parámetros!$B$7)/1000000,IF(Flujos!D5="Modelo B",B5*(Flujos!E5*Parámetros!$B$8+Flujos!F5*Parámetros!$B$9)/1000000,0)) -> 0 | F5: =B5*Flujos!G5*Parámetros!$B$10 -> 5.76 | G5: =D5+E5+F5 -> 25.474286 | H5: =G5/B5 -> 0.0088452381 | I5: =G5/$G$6 -> 0.3066974
A6: Portafolio | B6: =SUM(B2:B5) -> 8400 | C6: =B6/Parámetros!B4 -> 0.84 | D6: =SUM(D2:D5) -> 57.5 | E6: =SUM(E2:E5) -> 19.8 | F6: =SUM(F2:F5) -> 5.76 | G6: =SUM(G2:G5) -> 83.06 | H6: =G6/B6 -> 0.0098880952 | I6: =SUM(I2:I5) -> 1
A8: En la fila Portafolio, la columna C muestra qué parte del cupo del plan usa el portafolio completo.

Sheet Proyección
A1: Crecimiento mensual de los flujos ligados a reservas | B1: 0.03 | C1: Escenarios sugeridos: conservador 1%, base 3%, estrés 6%
A2: Ejecuciones de F2 por mes (con o sin batching) | B2: =Flujos!C3 -> 3000 | C2: Sin batching: igual a la hoja Flujos (3.000). Con batching cada 30 minutos: escribir 1440
A3: Ejecuciones de F4 por mes (según frecuencia) | B3: =Flujos!C5 -> 2880 | C3: Cada 15 minutos: igual a la hoja Flujos (2.880). Cada 30 minutos: escribir 1440
A5: Mes | B5: Factor estacional | C5: Factor de crecimiento | D5: F1 | E5: F2 | F5: F3 | G5: F4 | H5: Total del portafolio | I5: Cupo del plan | J5: ¿Supera el cupo?
A6: Octubre | B6: 1 | C6: =(1+$B$1)^0 -> 1 | D6: =ROUND(Flujos!$C$2*B6*C6,0) -> 1800 | E6: =ROUND($B$2*B6*C6,0) -> 3000 | F6: =ROUND(Flujos!$C$4*B6*C6,0) -> 720 | G6: =$B$3 -> 2880 | H6: =SUM(D6:G6) -> 8400 | I6: =Parámetros!$B$4 -> 10000 | J6: =IF(H6>I6,"SÍ: las ejecuciones nuevas fallan","No") -> No
A7: Noviembre | B7: 1 | C7: =(1+$B$1)^1 -> 1.03 | D7: =ROUND(Flujos!$C$2*B7*C7,0) -> 1854 | E7: =ROUND($B$2*B7*C7,0) -> 3090 | F7: =ROUND(Flujos!$C$4*B7*C7,0) -> 742 | G7: =$B$3 -> 2880 | H7: =SUM(D7:G7) -> 8566 | I7: =Parámetros!$B$4 -> 10000 | J7: =IF(H7>I7,"SÍ: las ejecuciones nuevas fallan","No") -> No
A8: Diciembre | B8: 1.4 | C8: =(1+$B$1)^2 -> 1.0609 | D8: =ROUND(Flujos!$C$2*B8*C8,0) -> 2673 | E8: =ROUND($B$2*B8*C8,0) -> 4456 | F8: =ROUND(Flujos!$C$4*B8*C8,0) -> 1069 | G8: =$B$3 -> 2880 | H8: =SUM(D8:G8) -> 11078 | I8: =Parámetros!$B$4 -> 10000 | J8: =IF(H8>I8,"SÍ: las ejecuciones nuevas fallan","No") -> SÍ: las ejecuciones nuevas fallan
A9: Enero | B9: 1.8 | C9: =(1+$B$1)^3 -> 1.092727 | D9: =ROUND(Flujos!$C$2*B9*C9,0) -> 3540 | E9: =ROUND($B$2*B9*C9,0) -> 5901 | F9: =ROUND(Flujos!$C$4*B9*C9,0) -> 1416 | G9: =$B$3 -> 2880 | H9: =SUM(D9:G9) -> 13737 | I9: =Parámetros!$B$4 -> 10000 | J9: =IF(H9>I9,"SÍ: las ejecuciones nuevas fallan","No") -> SÍ: las ejecuciones nuevas fallan
A10: Febrero | B10: 1.5 | C10: =(1+$B$1)^4 -> 1.1255088 | D10: =ROUND(Flujos!$C$2*B10*C10,0) -> 3039 | E10: =ROUND($B$2*B10*C10,0) -> 5065 | F10: =ROUND(Flujos!$C$4*B10*C10,0) -> 1216 | G10: =$B$3 -> 2880 | H10: =SUM(D10:G10) -> 12200 | I10: =Parámetros!$B$4 -> 10000 | J10: =IF(H10>I10,"SÍ: las ejecuciones nuevas fallan","No") -> SÍ: las ejecuciones nuevas fallan
A11: Marzo | B11: 1 | C11: =(1+$B$1)^5 -> 1.1592741 | D11: =ROUND(Flujos!$C$2*B11*C11,0) -> 2087 | E11: =ROUND($B$2*B11*C11,0) -> 3478 | F11: =ROUND(Flujos!$C$4*B11*C11,0) -> 835 | G11: =$B$3 -> 2880 | H11: =SUM(D11:G11) -> 9280 | I11: =Parámetros!$B$4 -> 10000 | J11: =IF(H11>I11,"SÍ: las ejecuciones nuevas fallan","No") -> No
A12: Abril | B12: 1 | C12: =(1+$B$1)^6 -> 1.1940523 | D12: =ROUND(Flujos!$C$2*B12*C12,0) -> 2149 | E12: =ROUND($B$2*B12*C12,0) -> 3582 | F12: =ROUND(Flujos!$C$4*B12*C12,0) -> 860 | G12: =$B$3 -> 2880 | H12: =SUM(D12:G12) -> 9471 | I12: =Parámetros!$B$4 -> 10000 | J12: =IF(H12>I12,"SÍ: las ejecuciones nuevas fallan","No") -> No
A13: Mayo | B13: 1 | C13: =(1+$B$1)^7 -> 1.2298739 | D13: =ROUND(Flujos!$C$2*B13*C13,0) -> 2214 | E13: =ROUND($B$2*B13*C13,0) -> 3690 | F13: =ROUND(Flujos!$C$4*B13*C13,0) -> 886 | G13: =$B$3 -> 2880 | H13: =SUM(D13:G13) -> 9670 | I13: =Parámetros!$B$4 -> 10000 | J13: =IF(H13>I13,"SÍ: las ejecuciones nuevas fallan","No") -> No
A14: Junio | B14: 1 | C14: =(1+$B$1)^8 -> 1.2667701 | D14: =ROUND(Flujos!$C$2*B14*C14,0) -> 2280 | E14: =ROUND($B$2*B14*C14,0) -> 3800 | F14: =ROUND(Flujos!$C$4*B14*C14,0) -> 912 | G14: =$B$3 -> 2880 | H14: =SUM(D14:G14) -> 9872 | I14: =Parámetros!$B$4 -> 10000 | J14: =IF(H14>I14,"SÍ: las ejecuciones nuevas fallan","No") -> No
A15: Julio | B15: 1.3 | C15: =(1+$B$1)^9 -> 1.3047732 | D15: =ROUND(Flujos!$C$2*B15*C15,0) -> 3053 | E15: =ROUND($B$2*B15*C15,0) -> 5089 | F15: =ROUND(Flujos!$C$4*B15*C15,0) -> 1221 | G15: =$B$3 -> 2880 | H15: =SUM(D15:G15) -> 12243 | I15: =Parámetros!$B$4 -> 10000 | J15: =IF(H15>I15,"SÍ: las ejecuciones nuevas fallan","No") -> SÍ: las ejecuciones nuevas fallan
A16: Agosto | B16: 1 | C16: =(1+$B$1)^10 -> 1.3439164 | D16: =ROUND(Flujos!$C$2*B16*C16,0) -> 2419 | E16: =ROUND($B$2*B16*C16,0) -> 4032 | F16: =ROUND(Flujos!$C$4*B16*C16,0) -> 968 | G16: =$B$3 -> 2880 | H16: =SUM(D16:G16) -> 10299 | I16: =Parámetros!$B$4 -> 10000 | J16: =IF(H16>I16,"SÍ: las ejecuciones nuevas fallan","No") -> SÍ: las ejecuciones nuevas fallan
A17: Septiembre | B17: 1 | C17: =(1+$B$1)^11 -> 1.3842339 | D17: =ROUND(Flujos!$C$2*B17*C17,0) -> 2492 | E17: =ROUND($B$2*B17*C17,0) -> 4153 | F17: =ROUND(Flujos!$C$4*B17*C17,0) -> 997 | G17: =$B$3 -> 2880 | H17: =SUM(D17:G17) -> 10522 | I17: =Parámetros!$B$4 -> 10000 | J17: =IF(H17>I17,"SÍ: las ejecuciones nuevas fallan","No") -> SÍ: las ejecuciones nuevas fallan
A19: Meses que superan el cupo | B19: =COUNTIF(J6:J17,"SÍ*") -> 6
A20: Máximo mensual del año | B20: =MAX(H6:H17) -> 13737
